reapit_cdk/wildcard_certificate/__init__.py
reapit_cdk/wildcard_certificate/py.typed
reapit_cdk/wildcard_certificate/_jsii/__init__.py
reapit_cdk/wildcard_certificate/_jsii/wildcard-certificate@0.1.0.jsii.tgz
reapit_cdk.wildcard_certificate-0.1.0.dist-info/LICENSE
reapit_cdk.wildcard_certificate-0.1.0.dist-info/METADATA
reapit_cdk.wildcard_certificate-0.1.0.dist-info/WHEEL
reapit_cdk.wildcard_certificate-0.1.0.dist-info/top_level.txt
reapit_cdk.wildcard_certificate-0.1.0.dist-info/RECORD
